DIFI/SwarmL2_F107_Read.py
DIFI/SwarmL2_MIO_SHA_Read_v2.py
DIFI/__init__.py
DIFI/design_SHA_Sq_e_Re_v2.py
DIFI/design_SHA_Sq_i_Re_v2.py
DIFI/forward_Sq_d_Re.py
DIFI/getSQfield.py
DIFI/get_f107_index_all.py
DIFI/getmut.py
DIFI/gg2gm_2010.py
DIFI/jd2000_dt.py
DIFI/sun_md2000.py
DIFI/coefs/DIFI8.DBL
DIFI/coefs/difi-coefs.txt
DIFI/coefs/f107.DBL
DIFI/coefs/xDIFI2.DBL
pydifi-8.1.2.dist-info/licenses/LICENSE
pydifi-8.1.2.dist-info/METADATA
pydifi-8.1.2.dist-info/WHEEL
pydifi-8.1.2.dist-info/top_level.txt
pydifi-8.1.2.dist-info/RECORD
