Metadata-Version: 2.4
Name: pyDIFI
Version: 8.1.2
Summary: The python module for DIFI-8
Author-email: Collin Kadlecek <Collin.Kadlecek@colorado.edu>, Li-Yin Young <liyin.young@colorado.edu>, Liam Kilcommons <liam.kilcommons@colorado.edu>
Project-URL: Homepage, https://github.com/CIRES-Geomagnetism/DIFI
Classifier: Programming Language :: Python :: 3
Classifier: Programming Language :: Python :: 3.9
Classifier: Programming Language :: Python :: 3.10
Classifier: Programming Language :: Python :: 3.11
Classifier: Programming Language :: Python :: 3.12
Classifier: Programming Language :: Python :: 3.13
Classifier: License :: OSI Approved :: MIT License
Classifier: Operating System :: OS Independent
License-File: LICENSE
Requires-Dist: numpy
Requires-Dist: geomaglib>=1.2.1
Dynamic: license-file
